[[10000,{"title":"인사","name":"10000.jpg"}],[10001,{"title":"그래서…？","name":"10001.jpg"}],[10002,{"title":"갓갓반응","name":"10002.jpg"}],[10003,{"title":"풀템","name":"10003.jpg"}],[10004,{"title":"목표는 쿨","name":"10004.jpg"}],[10005,{"title":"솔직하게","name":"10005.jpg"}],[10006,{"title":"덜렁티브","name":"10006.jpg"}],[10007,{"title":"애보기","name":"10007.jpg"}],[10008,{"title":"기습공격","name":"10008.jpg"}],[10009,{"title":"비밀의 그것","name":"10009.jpg"}],[10010,{"title":"걱정","name":"10010.jpg"}],[10011,{"title":"핫산","name":"10011.png"}],[10012,{"title":"가족","name":"10012.png"}],[10013,{"title":"함께있고 싶어","name":"10013.png"}],[10014,{"title":"텐카의 진심","name":"10014.png"}],[10015,{"title":"귀여운게 잔뜩","name":"10015.png"}],[10016,{"title":"단결력","name":"10016.png"}],[10017,{"title":"어른에 대한 동경","name":"10017.png"}],[10018,{"title":"말하자마자","name":"10018.png"}],[10019,{"title":"솔직하지 못해","name":"10019.png"}],[10020,{"title":"연애스승","name":"10020.png"}],[10021,{"title":"Time is money","name":"10021.png"}],[10022,{"title":"사장님과 283프로","name":"10022.png"}],[10023,{"title":"시작이에요!","name":"10023.png"}],[10024,{"title":"모두 함께","name":"10024.png"}],[10025,{"title":"서바이벌","name":"10025.jpg"}],[10026,{"title":"약점","name":"10026.jpg"}],[10027,{"title":"질투","name":"10027.jpg"}],[10028,{"title":"감상회","name":"10028.jpg"}],[10029,{"title":"사념","name":"10029.jpg"}],[10030,{"title":"결정적인 순간","name":"10030.jpg"}],[10031,{"title":"더더욱","name":"10031.jpg"}],[10032,{"title":"지참품","name":"10032.jpg"}],[10033,{"title":"그말이 아니라","name":"10033.jpg"}],[10034,{"title":"친구 사귀기","name":"10034.jpg"}],[10035,{"title":"저 사이즈 처럼","name":"10035.jpg"}],[10036,{"title":"강력한 상대","name":"10036.jpg"}],[10037,{"title":"누구를 위해서","name":"10037.jpg"}],[10038,{"title":"그게 아냐","name":"10038.jpg"}],[10039,{"title":"스나이퍼","name":"10039.jpg"}],[10040,{"title":"화내기","name":"10040.jpg"}],[10041,{"title":"아방튀르","name":"10041.jpg"}],[10042,{"title":"수국이랑","name":"10042.jpg"}],[10043,{"title":"계절 패턴","name":"10043.jpg"}],[10044,{"title":"근육","name":"10044.jpg"}],[10045,{"title":"멋짐","name":"10045.jpg"}],[10046,{"title":"수박의 기분","name":"10046.jpg"}],[10047,{"title":"정교해","name":"10047.jpg"}],[10048,{"title":"뱀","name":"10048.jpg"}],[10049,{"title":"돌봐주는 팀","name":"10049.jpg"}],[10050,{"title":"어시스턴트","name":"10050.jpg"}],[10051,{"title":"언제나 보고있어","name":"10051.jpg"}],[10052,{"title":"꿈의 시츄에이션","name":"10052.jpg"}],[10053,{"title":"중장비","name":"10053.jpg"}],[10054,{"title":"타겟 변경","name":"10054.jpg"}],[10055,{"title":"사건","name":"10055.jpg"}],[10056,{"title":"오늘밤은 못보내","name":"10056.jpg"}],[10057,{"title":"반지","name":"10057.jpg"}],[10058,{"title":"권속","name":"10058.jpg"}],[10059,{"title":"늑대","name":"10059.jpg"}],[10060,{"title":"라이벌","name":"10060.jpg"}],[10061,{"title":"비밀의 미용법","name":"10061.jpg"}],[10062,{"title":"금메달","name":"10062.jpg"}],[10063,{"title":"상담","name":"10063.jpg"}],[10064,{"title":"사랑스런 걸","name":"10064.jpg"}],[10065,{"title":"밤을 한번 더","name":"10065.jpg"}],[10066,{"title":"소음","name":"10066.jpg"}],[10067,{"title":"조언","name":"10067.jpg"}],[10068,{"title":"못참아","name":"10068.jpg"}],[10069,{"title":"합체","name":"10069.jpg"}],[10070,{"title":"그네","name":"10070.jpg"}],[10071,{"title":"부푸는 마노","name":"10071.jpg"}],[10072,{"title":"산타클로스","name":"10072.jpg"}],[10073,{"title":"치유키씨가 보고계셔","name":"10073.jpg"}],[10074,{"title":"부끄럽구마~","name":"10074.jpg"}],[10075,{"title":"공략법","name":"10075.jpg"}],[10076,{"title":"절대 말안해","name":"10076.jpg"}],[10077,{"title":"손잡기","name":"10077.jpg"}],[10078,{"title":"엄마의 마음","name":"10078.jpg"}],[10079,{"title":"교통안전 그림연극","name":"10079.jpg"}],[10080,{"title":"그 새의 이름은","name":"10080.jpg"}],[10081,{"title":"특별한 초콜렛","name":"10081.jpg"}],[10082,{"title":"캐치볼","name":"10082.jpg"}],[10083,{"title":"언니","name":"10083.jpg"}],[10084,{"title":"이상한 곳에서","name":"10084.jpg"}],[10085,{"title":"미소의 질","name":"10085.jpg"}],[10086,{"title":"구사 일생","name":"10086.jpg"}],[10087,{"title":"단가","name":"10087.jpg"}],[10088,{"title":"사이버 셀카","name":"10088.jpg"}],[10089,{"title":"재밌는거 찾기","name":"10089.jpg"}],[10090,{"title":"귀여움의 화신","name":"10090.jpg"}],[10091,{"title":"갸루의 가능성","name":"10091.jpg"}],[10092,{"title":"최종모드","name":"10092.jpg"}],[10093,{"title":"새로운 일","name":"10093.jpg"}],[10094,{"title":"바빠","name":"10094.jpg"}],[10095,{"title":"비밀기지","name":"10095.jpg"}],[10096,{"title":"불안한 마음","name":"10096.jpg"}],[10097,{"title":"서프라이즈","name":"10097.jpg"}],[10098,{"title":"케이크 가게","name":"10098.jpg"}],[10099,{"title":"안심해","name":"10099.jpg"}],[10100,{"title":"선물","name":"10100.jpg"}],[10101,{"title":"데빌타로","name":"10101.jpg"}],[10102,{"title":"일자상전","name":"10102.jpg"}],[10103,{"title":"시트의 유령","name":"10103.jpg"}],[10104,{"title":"무궁무진한 관심","name":"10104.jpg"}],[10105,{"title":"연기파 여배우","name":"10105.jpg"}],[10106,{"title":"결정적인 대사","name":"10106.jpg"}],[10107,{"title":"유카타랑 상관없이","name":"10107.jpg"}],[10108,{"title":"원래 해야 할거","name":"10108.jpg"}],[10109,{"title":"셋이라면","name":"10109.jpg"}],[10110,{"title":"탄자쿠에 소원","name":"10110.jpg"}],[10111,{"title":"사랑","name":"10111.jpg"}],[10112,{"title":"공유하자","name":"10112.jpg"}],[10113,{"title":"귀엽고 멋져","name":"10113.jpg"}],[10114,{"title":"순서","name":"10114.jpg"}],[10115,{"title":"천조","name":"10115.jpg"}],[10116,{"title":"배려 깊은 아이","name":"10116.jpg"}],[10117,{"title":"언제나 곁에 있어주는 사람","name":"10117.jpg"}],[10118,{"title":"복어의 실태","name":"10118.jpg"}],[10119,{"title":"고오급 농담","name":"10119.jpg"}],[10120,{"title":"적재적소","name":"10120.jpg"}],[10121,{"title":"분실물","name":"10121.jpg"}],[10122,{"title":"사진","name":"10122.jpg"}],[10123,{"title":"석양을 향해 외쳐봐","name":"10123.jpg"}],[10124,{"title":"모래벌판 달리기","name":"10124.jpg"}],[10125,{"title":"그때 바람이 불어 왔다","name":"10125.jpg"}],[10126,{"title":"턱잡","name":"10126.jpg"}],[10127,{"title":"배터리","name":"10127.jpg"}],[10128,{"title":"좀 더 줄일 수 있는데","name":"10128.jpg"}],[10129,{"title":"깔맞춤","name":"10129.jpg"}],[10130,{"title":"소녀에서 어른으로","name":"10130.jpg"}],[10131,{"title":"텐카에게 맡겨만 줘","name":"10131.jpg"}],[10132,{"title":"상관 없슴다!","name":"10132.jpg"}],[10133,{"title":"냄새 따라서","name":"10133.jpg"}],[10134,{"title":"다양한 패턴으로","name":"10134.jpg"}],[10135,{"title":"동물 대난투","name":"10135.jpg"}],[10136,{"title":"일요일의 냄새","name":"10136.jpg"}],[10137,{"title":"안풀리네","name":"10137.jpg"}],[10138,{"title":"듀엣","name":"10138.jpg"}],[10139,{"title":"볼따구 만질만질","name":"10139.jpg"}],[10140,{"title":"치요코의 진심","name":"10140.jpg"}],[10141,{"title":"고구마 캐기","name":"10141.jpg"}],[10142,{"title":"지금은 아냐","name":"10142.jpg"}],[10143,{"title":"최고의 장난","name":"10143.jpg"}],[10144,{"title":"팬레터","name":"10144.jpg"}],[10145,{"title":"어서와 미츠미네 집에","name":"10145.jpg"}],[10146,{"title":"감사의 연쇄","name":"10146.jpg"}],[10147,{"title":"산악 삼매경","name":"10147.jpg"}],[10148,{"title":"꿈에서도 만나자","name":"10148.jpg"}],[10149,{"title":"텐카는 인형","name":"10149.jpg"}],[10150,{"title":"어리광쟁이 공주님","name":"10150.jpg"}],[10151,{"title":"시장조사","name":"10151.jpg"}],[10152,{"title":"키메라","name":"10152.jpg"}],[10153,{"title":"귀여운 소리","name":"10153.jpg"}],[10154,{"title":"펭귄모녀","name":"10154.jpg"}],[10155,{"title":"카르멘 립스틱","name":"10155.jpg"}],[10156,{"title":"미츠미네 산타","name":"10156.jpg"}],[10157,{"title":"비밀 작업","name":"10157.jpg"}],[10158,{"title":"산타의 정체","name":"10158.jpg"}],[10159,{"title":"페인팅 하이","name":"10159.jpg"}],[10160,{"title":"대청소","name":"10160.jpg"}],[10161,{"title":"좋은 새해를","name":"10161.jpg"}],[10162,{"title":"세뱃돈","name":"10162.jpg"}],[10163,{"title":"언젠가","name":"10163.jpg"}],[10164,{"title":"승자의 유열","name":"10164.jpg"}],[10165,{"title":"매일 먹고싶어","name":"10165.jpg"}],[10166,{"title":"초코선배의 매력","name":"10166.jpg"}],[10167,{"title":"옆에서 지켜봐 줄게","name":"10167.jpg"}],[10168,{"title":"어디선가 맡아 본 냄새","name":"10168.jpg"}],[10169,{"title":"더 높게","name":"10169.jpg"}],[10170,{"title":"제 1회 주인님 대회","name":"10170.jpg"}],[10171,{"title":"초콜렛 시식","name":"10171.jpg"}],[10172,{"title":"메세지가 말하고 싶은거","name":"10172.jpg"}],[10173,{"title":"무욕의 승리","name":"10173.jpg"}],[10174,{"title":"어울리는 모습","name":"10174.jpg"}],[10175,{"title":"패밀리 레스토랑","name":"10175.jpg"}],[10176,{"title":"무리하면 안돼","name":"10176.jpg"}],[10177,{"title":"접이식 우산","name":"10177.jpg"}],[10178,{"title":"햄버거 먹는 방법","name":"10178.jpg"}],[10179,{"title":"다음엔 반드시","name":"10179.jpg"}],[10180,{"title":"답례의 허들","name":"10180.jpg"}],[10181,{"title":"자신감의 비밀","name":"10181.jpg"}],[10182,{"title":"어른의 소양","name":"10182.jpg"}],[10183,{"title":"평소처럼","name":"10183.jpg"}],[10184,{"title":"일상의 풍경","name":"10184.jpg"}],[10185,{"title":"이웃","name":"10185.jpg"}],[10186,{"title":"성실함과 마이페이스","name":"10186.jpg"}],[10187,{"title":"만약에말야","name":"10187.jpg"}],[10188,{"title":"세계의 공유","name":"10188.jpg"}],[10189,{"title":"동네 최고","name":"10189.jpg"}],[10190,{"title":"꽃이 어울리는 미소녀","name":"10190.jpg"}],[10191,{"title":"언니","name":"10191.jpg"}],[10192,{"title":"대도시RPG","name":"10192.jpg"}],[10193,{"title":"말하지 못했던 것","name":"10193.jpg"}],[10194,{"title":"합작","name":"10194.jpg"}],[10195,{"title":"우울할 때는","name":"10195.jpg"}],[10196,{"title":"보여줄 수 없어","name":"10196.jpg"}],[10197,{"title":"휴일을 보내는 방법","name":"10197.jpg"}],[10198,{"title":"사과의 뜻으로","name":"10198.jpg"}],[10199,{"title":"유닛 속 붐","name":"10199.jpg"}],[10200,{"title":"행복해지기 위한 푸른색","name":"10200.jpg"}],[10201,{"title":"변덕","name":"10201.jpg"}],[10202,{"title":"설득법","name":"10202.jpg"}],[10203,{"title":"놀고 싶은 나이","name":"10203.jpg"}],[10204,{"title":"진로","name":"10204.jpg"}],[10205,{"title":"전장의 드라마","name":"10205.jpg"}],[10206,{"title":"덧대기","name":"10206.jpg"}],[10207,{"title":"애써보이는 기질","name":"10207.jpg"}],[10208,{"title":"선배들 대응법","name":"10208.jpg"}],[10209,{"title":"미래의 아이돌","name":"10209.jpg"}],[10210,{"title":"수영복 감상","name":"10210.jpg"}],[10211,{"title":"파라슈트 불꽃놀이","name":"10211.jpg"}],[10212,{"title":"여름이라고 느껴질 때","name":"10212.jpg"}],[10213,{"title":"도전의 보상","name":"10213.jpg"}],[10214,{"title":"아이스크림 두통","name":"10214.jpg"}],[10215,{"title":"불꽃 포획 작전","name":"10215.jpg"}],[10216,{"title":"금붕어 건지기랑 소원","name":"10216.jpg"}],[10217,{"title":"오징어 외계인","name":"10217.jpg"}],[10218,{"title":"잠깐만 할려고 했는데","name":"10218.jpg"}],[10219,{"title":"좋아하기 때문에","name":"10219.jpg"}],[10220,{"title":"우선 체험해보자","name":"10220.jpg"}],[10221,{"title":"연구의 성과","name":"10221.jpg"}],[10222,{"title":"맴버들의 정보","name":"10222.jpg"}],[10223,{"title":"마음의 소리","name":"10223.jpg"}],[10224,{"title":"태양과 달","name":"10224.jpg"}],[10225,{"title":"과연 어떻게 될 것인가？！","name":"10225.jpg"}],[10226,{"title":"어떤게 좋아？","name":"10226.jpg"}],[10227,{"title":"서로서로 리스펙트","name":"10227.jpg"}],[10228,{"title":"전철에서","name":"10228.jpg"}],[10229,{"title":"10까지 세면","name":"10229.jpg"}],[10230,{"title":"얼굴 새빨개","name":"10230.jpg"}],[10231,{"title":"사전조사","name":"10231.jpg"}],[10232,{"title":"마음속으로","name":"10232.jpg"}],[10233,{"title":"맞춰봐","name":"10233.jpg"}],[10234,{"title":"테마파크 가족 나들이","name":"10234.jpg"}],[10235,{"title":"반항기？","name":"10235.jpg"}],[10236,{"title":"개변","name":"10236.jpg"}],[10237,{"title":"방클걸스러운 아침일과","name":"10237.jpg"}],[10238,{"title":"타협은 없다","name":"10238.jpg"}],[10239,{"title":"공동 운명체","name":"10239.jpg"}],[10240,{"title":"사랑스러운 딸","name":"10240.jpg"}],[10241,{"title":"선물 교환","name":"10241.jpg"}],[10242,{"title":"맵시있게","name":"10242.jpg"}],[10243,{"title":"필살기","name":"10243.jpg"}],[10244,{"title":"들어버렸다","name":"10244.jpg"}],[10245,{"title":"선상 파티에서","name":"10245.jpg"}],[10246,{"title":"굉장했어","name":"10246.jpg"}],[10247,{"title":"겉잠 꿈","name":"10247.jpg"}],[10248,{"title":"배려심","name":"10248.jpg"}],[10249,{"title":"드라마 역할","name":"10249.jpg"}],[10250,{"title":"열심히 했다는 어필","name":"10250.jpg"}],[10251,{"title":"손수 만든 초콜렛","name":"10251.jpg"}],[10252,{"title":"점원 권한","name":"10252.jpg"}],[10253,{"title":"붕어빵 진단","name":"10253.jpg"}],[10254,{"title":"공부 도와주기","name":"10254.jpg"}],[10255,{"title":"트릭사진","name":"10255.jpg"}],[10256,{"title":"애타게 기다리고 있어","name":"10256.jpg"}],[10257,{"title":"찾고 있는거 벚꽃 아래에 있어","name":"10257.jpg"}],[10258,{"title":"친구들은 연예인","name":"10258.jpg"}],[10259,{"title":"좋아하지만 무서워","name":"10259.jpg"}],[10260,{"title":"나나쿠사 자매","name":"10260.jpg"}],[10261,{"title":"이 업계의 사람","name":"10261.jpg"}],[10262,{"title":"기합","name":"10262.jpg"}],[10263,{"title":"그쪽이요","name":"10263.jpg"}],[10264,{"title":"새로운 세력","name":"10264.jpg"}],[10265,{"title":"접대","name":"10265.jpg"}],[10266,{"title":"몰입","name":"10266.jpg"}],[10267,{"title":"카세트 테이프","name":"10267.jpg"}],[10268,{"title":"어느쪽이 더 아이같아？","name":"10268.jpg"}],[10269,{"title":"막과자 선생님","name":"10269.jpg"}],[10270,{"title":"책꿈","name":"10270.jpg"}],[10271,{"title":"나도","name":"10271.jpg"}],[10272,{"title":"화장하고 싶어","name":"10272.jpg"}],[10273,{"title":"일리가 있어","name":"10273.jpg"}],[10274,{"title":"모두 다 반성","name":"10274.jpg"}],[10275,{"title":"결혼에 관하여","name":"10275.jpg"}],[10276,{"title":"감기걸린 날","name":"10276.jpg"}],[10277,{"title":"아가씨 놀이","name":"10277.jpg"}],[10278,{"title":"트위스터 사용법","name":"10278.jpg"}],[10279,{"title":"싸인","name":"10279.jpg"}],[10280,{"title":"불끈불끈계획","name":"10280.jpg"}],[10281,{"title":"일루미 세자매","name":"10281.jpg"}],[10282,{"title":"비눗방울","name":"10282.jpg"}],[10283,{"title":"매미","name":"10283.jpg"}],[10284,{"title":"파트너","name":"10284.jpg"}],[10285,{"title":"알스트로메리아 닌자단","name":"10285.jpg"}],[10286,{"title":"이유없이 줄 수 없지","name":"10286.jpg"}],[10287,{"title":"인력거","name":"10287.jpg"}],[10288,{"title":"미츠미네 유이카는 즐겁다","name":"10288.jpg"}],[10289,{"title":"선두는 누가 할꺼야？","name":"10289.jpg"}],[10290,{"title":"배","name":"10290.jpg"}],[10291,{"title":"기쁜 얘기","name":"10291.jpg"}],[10292,{"title":"아사쿠라&히구치","name":"10292.jpg"}],[10293,{"title":"다람쥐과","name":"10293.jpg"}],[10294,{"title":"표정","name":"10294.jpg"}],[10295,{"title":"갓 들어온 연예계","name":"10295.jpg"}],[10296,{"title":"멋지고 귀여워","name":"10296.jpg"}],[10297,{"title":"상세한 감상","name":"10297.jpg"}],[10298,{"title":"호러","name":"10298.jpg"}],[10299,{"title":"군고구마 파티","name":"10299.jpg"}],[10300,{"title":"변장 퍼레이드","name":"10300.jpg"}],[20006,{"title":"좋아하는 점","name":"20006.jpg"}],[20007,{"title":"일루미네이션","name":"20007.jpg"}],[30001,{"title":"잘 보고 있어","name":"30001.jpg"}],[30002,{"title":"쿨&보컬","name":"30002.jpg"}],[30003,{"title":"행복론","name":"30003.jpg"}],[30004,{"title":"굉장한 사람","name":"30004.jpg"}],[30005,{"title":"친구가 되었다","name":"30005.jpg"}],[30006,{"title":"추억","name":"30006.jpg"}],[30007,{"title":"텐카쨩의 목표","name":"30007.jpg"}],[30008,{"title":"리벤지","name":"30008.jpg"}],[30009,{"title":"미광(Stray light)","name":"30009.jpg"}],[90001,{"title":"노려라 톱","name":"90001.jpg"}],[90002,{"title":"촬영 NG","name":"90002.jpg"}],[90003,{"title":"전화기의 저편엔","name":"90003.jpg"}],[90004,{"title":"개를 좋아하는 사람들을 위한 보물영상","name":"90004.jpg"}],[90005,{"title":"쥬리의 일상","name":"90005.jpg"}],[90006,{"title":"심상과 욕망","name":"90006.jpg"}],[90007,{"title":"알스메 시작했어☆","name":"90007.jpg"}],[90008,{"title":"보육원 도우미","name":"90008.jpg"}],[90009,{"title":"어느 텐카의 휴일","name":"90009.jpg"}],[90010,{"title":"모닝 일과","name":"90010.jpg"}],[90011,{"name":"90011undefined"}],[90012,{"title":"아무것도 안보여","name":"90012.jpg"}],[90013,{"title":"자유분방한 인방","name":"90013.jpg"}],[90014,{"title":"Straylight","name":"90014.jpg"}],[90015,{"title":"미지의 에너지","name":"90015.jpg"}],[90016,{"title":"뭐라도 해야 돼","name":"90016.jpg"}],[90017,{"title":"조류와 야생화를 찾아서","name":"90017.jpg"}],[90018,{"title":"Yell","name":"90018.jpg"}],[90019,{"title":"영화 제작","name":"90019.jpg"}],[90020,{"title":"행복해~ 연쇄","name":"90020.jpg"}],[90021,{"title":"어때…？","name":"90021.jpg"}],[90022,{"title":"고민되는 촬영량","name":"90022.jpg"}],[90023,{"title":"찍었어？","name":"90023.jpg"}],[90024,{"title":"순서의 진실","name":"90024.jpg"}],[90025,{"title":"외로움을 잘 타는 대형견","name":"90025.jpg"}],[90026,{"title":"거베라씨의 목소리","name":"90026.jpg"}],[90027,{"title":"잘 보면 귀여워","name":"90027.jpg"}],[90028,{"title":"악수회 그 이상","name":"90028.jpg"}],[90029,{"title":"코가네 쿠킹","name":"90029.jpg"}],[90030,{"title":"믿을만한 녀석","name":"90030.jpg"}]]
